CaptchaLibrary/CaptchaLibrary.py
CaptchaLibrary/__init__.py
CaptchaLibrary/version.py
CaptchaLibrary/services/__init__.py
CaptchaLibrary/services/forgotcaptcha/ForgotCaptcha.py
CaptchaLibrary/services/forgotcaptcha/__init__.py
CaptchaLibrary/services/twocaptcha/SimpleCaptcha.py
CaptchaLibrary/services/twocaptcha/__init__.py
CaptchaLibrary/utils/Configuration.py
CaptchaLibrary/utils/EncDec.py
CaptchaLibrary/utils/Img.py
CaptchaLibrary/utils/__init__.py
rf_captchalibrary-0.7.1.dist-info/LICENSE
rf_captchalibrary-0.7.1.dist-info/METADATA
rf_captchalibrary-0.7.1.dist-info/WHEEL
rf_captchalibrary-0.7.1.dist-info/top_level.txt
rf_captchalibrary-0.7.1.dist-info/RECORD
