Metadata-Version: 2.1
Name: rf-captchalibrary
Version: 0.7.1
Summary: Test Library for decoding base64 captchas to string format.
Home-page: https://github.com/MainSystemDev/rf-captchalibrary
Author: Joshua Kim Rivera
Author-email: joshua.rivera@mnltechnology.com
License: Type license() to see the full license text
Platform: any
Classifier: Development Status :: 5 - Production/Stable
Classifier: License :: OSI Approved :: MIT License
Classifier: Operating System :: OS Independent
Classifier: Programming Language :: Python :: 3
Classifier: Topic :: Software Development :: Testing
Classifier: Framework :: Robot Framework
Classifier: Framework :: Robot Framework :: Library
Requires-Dist: Pillow (>=7.1.0)
Requires-Dist: pyqrcode
Requires-Dist: requests (==2.22.0)
Requires-Dist: robotframework (>=3.2.2)
Requires-Dist: robotframework-pythonlibcore (>=2.1.0)
